{
    "_comment": "Generated with pbcommand version 1.9.2 at 2020-06-17T12:02:53.523068",
    "attributes": [
        {
            "id": "adapter_xml_report.adapter_dimers",
            "name": "Adapter Dimers (0-10bp) %",
            "value": 0.0
        },
        {
            "id": "adapter_xml_report.short_inserts",
            "name": "Short Inserts (11-100bp) %",
            "value": 0.0
        },
        {
            "id": "adapter_xml_report.local_base_rate_median",
            "name": "Local Base Rate",
            "value": 2.74376
        }
    ],
    "dataset_uuids": [
        "88be614a-fa14-4596-ba6e-3e90e5a3a8f9"
    ],
    "id": "adapter_xml_report",
    "plotGroups": [],
    "tables": [],
    "tags": [],
    "title": "Report adapter_xml_report",
    "uuid": "422dc1b7-74fe-409b-9b43-9338e5d802aa",
    "version": "1.0.1"
}